arana/__init__.py
arana/browser.py
arana/config.py
arana/console.py
arana/content.py
arana/element.py
arana/frame.py
arana/html.py
arana/page.py
arana/py.typed
arana/response.py
arana/rndm.py
arana-0.0.12.dist-info/licenses/LICENSE.txt
arana-0.0.12.dist-info/METADATA
arana-0.0.12.dist-info/WHEEL
arana-0.0.12.dist-info/top_level.txt
arana-0.0.12.dist-info/RECORD
