Metadata-Version: 2.4
Name: arana
Version: 0.0.12
Summary: Abstraction layer for web scrapers
Author-email: Fabrício Barros Cabral <fabriciofx@gmail.com>
License-Expression: MIT
Project-URL: homepage, https://github.com/fabriciofx/arana
Project-URL: bug-tracker, https://github.com/fabriciofx/arana/issues
Keywords: web,scraper,playwright,scrapy,scraping,browserforge
Requires-Python: >=3.14
License-File: LICENSE.txt
Requires-Dist: browserforge>=1.2.3
Requires-Dist: playwright>=1.56.0
Dynamic: license-file
